<?xml version="1.0" encoding="utf-8"?>
<openerp>
    <data>
        <record id="stock_production_lot_add_analysis" model="ir.ui.view">
            <field name="name">stock.production.lot.form</field>
            <field name="model">stock.production.lot</field>
            <field name="inherit_id" ref="stock.view_production_lot_form"/>
            <field name="arch" type="xml">
                <xpath expr="//sheet" position="attributes">
                    <attribute name="class">oe_form_sheet_full_screen</attribute>
                </xpath>
                <notebook position="inside">
                    <page string="Quality">
                        <separator string="Used lots"/>
                        <field name="used_lots" nolabel="1" colspan="4" widget="html"/>
                        <group>
                            <field name="analysis_passed"/>
                        </group>
                        <group col="4" string="Origin">
                            <field name="origin_type" widget="radio"/>
                            <field name="origin_country_id"/>
                        </group>
                        <group string="Sampling">
                            <group>
                                <field name="num_container_sample_proposed"/>
                                <field name="num_container_sample_to_do"/>
                                <field name="num_container_sample_realized"/>
                            </group>
                            <group>
                                <field name="num_sampling_proposed"/>
                                <field name="num_sampling_to_do"/>
                                <field name="num_sampling_realized"/>
                            </group>
                        </group>
                        <group>
                            <field name="sampling_notes" placeholder="Sampling notes" nolabel="1" colspan="4"/>
                            <group>
                                <field name="sampling_date"/>
                                <field name="sampling_realized"/>
                            </group>
                            <group>
                                <separator/>
                            </group>
                        </group>
                        <separator string="Analysis"/>
                        <group>
                            <button name="action_stock_lot_analysis_wizard"
                                    type="object"
                                    string="Edit questionnaire"
                                    class="oe_read_only oe_highlight"/>
                            <button name="set_raw_material_analysis" string="Set raw material analysis" type="object"/>
                        </group>
                        <group>
                            <field name="analysis_ids" nolabel="1">
                                <tree default_order="sequence">
                                    <field name="sequence" invisible="1"/>
                                    <field name="raw_material_analysis" invisible="1"/>
                                    <field name="expected_result_boolean" invisible="1"/>
                                    <field name="expected_result_expr" invisible="1"/>
                                    <field name="result" invisible="1"/>
                                    <field name="analysis_id"/>
                                    <field name="show_in_certificate"/>
                                    <field name="proposed"/>
                                    <field name="realized"/>
                                    <field name="method"/>
                                    <field name="analysis_type"/>
                                    <field name="expected_result"/>
                                    <field name="result_boolean_selection"/>
                                    <field name="result_str"/>
                                    <field name="passed"/>
                                    <field name="criterion"/>
                                    <field name="realized_by"/>
                                    <field name="decimal_precision" digits="[42, 10]" attrs="{'invisible': [('analysis_type', '!=', 'expr')]}"/>
                                    <field name="expr_error"/>
                                </tree>
                            </field>
                            <field name="analysis_notes" placeholder="Analysis notes" nolabel="1" colspan="4"/>
                        </group>
                        <group>
                            <field name="revised_by"/>
                        </group>
                    </page>
                </notebook>
            </field>
        </record>

        <record model="ir.actions.act_window" id="action_analytic_control_pend">
            <field name="name">Analytic control pending</field>
            <field name="res_model">stock.production.lot</field>
            <field name="view_type">form</field>
            <field name="view_mode">tree,form</field>
            <field name="view_id" ref="stock.view_production_lot_tree"/>
            <field name="search_view_id" ref="stock.search_product_lot_filter"/>
            <field name="domain">[('product_id.analytic_certificate', '=', True), ('analysis_passed', '=', False)]</field>
        </record>

        <menuitem name="Analysis certificate"
                  parent="quality_management_menu.menu_quality_management"
                  id="quality_lot_menus"/>

        <menuitem name="Analytic control pending"
                  parent="quality_lot_menus"
                  action="action_analytic_control_pend"
                  id="quality_analytic_pend_menu"/>

        <record model="ir.actions.act_window" id="action_analytic_control_realized">
            <field name="name">Analytic control realized</field>
            <field name="res_model">stock.production.lot</field>
            <field name="view_type">form</field>
            <field name="view_mode">tree,form</field>
            <field name="view_id" ref="stock.view_production_lot_tree"/>
            <field name="search_view_id" ref="stock.search_product_lot_filter"/>
            <field name="domain">[('product_id.analytic_certificate', '=', True), ('analysis_passed', '=', True)]</field>
        </record>

        <menuitem name="Analytic control realized"
                  parent="quality_lot_menus"
                  action="action_analytic_control_realized"
                  id="quality_analytic_realized_menu"/>

        <record id="stock_production_lot_analysis_wizard" model="ir.ui.view">
            <field name="name">Stock lot analysis wizard</field>
            <field name="model">stock.production.lot</field>
            <field name="priority">20</field>
            <field name="arch" type="xml">
                <script type="text/javascript" src="product_analysis/static/src/js/analysis_table.js"></script>
                <form id="stock_lot_analysis_wizard">
                    <separator string="Analysis"/>
                    <group>
                        <field name="analysis_ids" nolabel="1">
                            <tree editable="bottom" default_order="sequence">
                                <field name="sequence"/>
                                <field name="raw_material_analysis"/>
                                <field name="expected_result_boolean"/>
                                <field name="expected_result_expr"/>
                                <field name="result"/>
                                <field name="analysis_id"/>
                                <field name="show_in_certificate"/>
                                <field name="proposed"/>
                                <field name="realized"/>
                                <field name="method"/>
                                <field name="analysis_type"/>
                                <field name="expected_result"/>
                                <field name="result_boolean_selection"/>
                                <field name="result_str"/>
                                <field name="passed"/>
                                <field name="criterion"/>
                                <field name="realized_by"/>
                                <field name="decimal_precision" digits="[42, 10]" attrs="{'invisible': [('analysis_type', '!=', 'expr')]}"/>
                                <field name="expr_error"/>
                            </tree>
                        </field>
                    </group>
                    <footer class="oe_right oe_button_box">
                        <button name="action_save_lot_analysis_wizard"
                                type="object"
                                string="Save"
                                class="oe_highlight"/>
                        or
                        <button string="Cancel" special="cancel"/>
                    </footer>
                </form>
            </field>
        </record>

        <record id="view_stock_production_lot_dates" model="ir.ui.view">
            <field name="name">Product analysis - Stock production lot dates</field>
            <field name="model">stock.production.lot</field>
            <field name="arch" type="xml">
                <tree create="0" edit="0" delete="0">
                    <field name="product_id"/>
                    <field name="default_code"/>
                    <field name="name"/>
                    <field name="available_stock"/>
                    <field name="state"/>
                    <field name="use_date"/>
                    <field name="removal_date"/>
                    <field name="date_in"/>
                    <field name="date_in_system"/>
                    <field name="life_date"/>
                    <field name="alert_date"/>
                    <field name="acceptance_date"/>
                    <field name="sampling_date"/>
                </tree>
            </field>
        </record>

        <record id="action_stock_production_lot_dates" model="ir.actions.act_window">
            <field name="name">Stock production lot dates</field>
            <field name="res_model">stock.production.lot</field>
            <field name="view_type">form</field>
            <field name="view_mode">tree,form</field>
            <field name="view_id" ref="view_stock_production_lot_dates"/>
            <field name="domain">[('quant_ids.location_id.usage', 'in', ('internal', 'view', 'transit', 'procurement'))]</field>
        </record>

        <menuitem action="action_stock_production_lot_dates"
                  id="menu_stock_production_lot_dates"
                  parent="stock.menu_traceability"
                  groups="stock.group_stock_manager"
                  sequence="21"/>
    </data>
</openerp>
